TracGoogleAnalytics-0.3.0.dist-info/METADATA
TracGoogleAnalytics-0.3.0.dist-info/RECORD
TracGoogleAnalytics-0.3.0.dist-info/WHEEL
TracGoogleAnalytics-0.3.0.dist-info/entry_points.txt
TracGoogleAnalytics-0.3.0.dist-info/top_level.txt
googleanalytics/__init__.py
googleanalytics/admin.py
googleanalytics/google.py
googleanalytics/web_ui.py
googleanalytics/htdocs/googleanalytics.css
googleanalytics/templates/google_analytics.html
googleanalytics/templates/google_analytics_admin.html
