Metadata-Version: 2.1
Name: TracGoogleAnalytics
Version: 0.3.0
Summary: Trac plugin to enable your trac environment to be logged by Google Analytics
Home-page: http://google.ufsoft.org
Author: Pedro Algarvio
Author-email: ufs@ufsoft.org
License: BSD
Download-URL: https://pypi.python.org/pypi/TracGoogleAnalytics
Keywords: trac plugin google analytics
Platform: UNKNOWN
Classifier: Framework :: Trac
